LICENSE
MANIFEST.in
NEWS
NOTICE
background-associations.txt
setup.cfg
setup.py
admin/builddiscover.py
admin/fixperms
admin/gettlds.py
admin/makechangelog
admin/makedoc
admin/pythonsource
admin/runtests
admin/setversion
admin/tagrelease
contrib/associate
contrib/openid-parse
contrib/upgrade-store-1.1-to-2.0
examples/README
examples/__init__.py
examples/consumer.py
examples/discover
examples/server.py
examples/djopenid/README
examples/djopenid/__init__.py
examples/djopenid/manage.py
examples/djopenid/settings.py
examples/djopenid/urls.py
examples/djopenid/util.py
examples/djopenid/views.py
examples/djopenid/consumer/__init__.py
examples/djopenid/consumer/models.py
examples/djopenid/consumer/urls.py
examples/djopenid/consumer/views.py
examples/djopenid/server/__init__.py
examples/djopenid/server/models.py
examples/djopenid/server/tests.py
examples/djopenid/server/urls.py
examples/djopenid/server/views.py
examples/djopenid/templates/index.html
examples/djopenid/templates/xrds.xml
examples/djopenid/templates/consumer/index.html
examples/djopenid/templates/consumer/request_form.html
examples/djopenid/templates/server/endpoint.html
examples/djopenid/templates/server/idPage.html
examples/djopenid/templates/server/index.html
examples/djopenid/templates/server/pape_request_info.html
examples/djopenid/templates/server/trust.html
openid/__init__.py
openid/association.py
openid/cryptutil.py
openid/dh.py
openid/extension.py
openid/fetchers.py
openid/kvform.py
openid/message.py
openid/oidutil.py
openid/sreg.py
openid/urinorm.py
openid/consumer/__init__.py
openid/consumer/consumer.py
openid/consumer/discover.py
openid/consumer/html_parse.py
openid/extensions/__init__.py
openid/extensions/ax.py
openid/extensions/sreg.py
openid/extensions/draft/__init__.py
openid/extensions/draft/pape2.py
openid/extensions/draft/pape5.py
openid/server/__init__.py
openid/server/server.py
openid/server/trustroot.py
openid/store/__init__.py
openid/store/filestore.py
openid/store/interface.py
python_openid_lac.egg-info/PKG-INFO
python_openid_lac.egg-info/SOURCES.txt
python_openid_lac.egg-info/dependency_links.txt
python_openid_lac.egg-info/top_level.txt