Metadata-Version: 1.1
Name: python-openid-lac
Version: 2.2.5
Summary: OpenID support for servers and consumers.
Home-page: http://github.com/mtgreenway/python-openid
Author: Matt Greenway
Author-email: mgreenway@uchicago.edu
License: UNKNOWN
Download-URL: http://github.com/mtgreenway/python-openid/tarball/2.2.5
Platform: UNKNOWN
Classifier: Development Status :: 5 - Production/Stable
Classifier: Environment :: Web Environment
Classifier: Intended Audience :: Developers
Classifier: License :: OSI Approved :: Apache Software License
Classifier: Operating System :: POSIX
Classifier: Programming Language :: Python
Classifier: Topic :: Internet :: WWW/HTTP
Classifier: Topic :: Internet :: WWW/HTTP :: Dynamic Content :: CGI Tools/Libraries
Classifier: Topic :: Software Development :: Libraries :: Python Modules
Classifier: Topic :: System :: Systems Administration :: Authentication/Directory
